air_drf_relation/__init__.py
air_drf_relation/apps.py
air_drf_relation/context_builder.py
air_drf_relation/decorators.py
air_drf_relation/encoders.py
air_drf_relation/extra_kwargs.py
air_drf_relation/fields.py
air_drf_relation/filters.py
air_drf_relation/model_fields.py
air_drf_relation/preload_objects_manager.py
air_drf_relation/queryset_optimization.py
air_drf_relation/serializers.py
air_drf_relation/settings.py
air_drf_relation/utils.py
air_drf_relation-1.0.3.dist-info/METADATA
air_drf_relation-1.0.3.dist-info/WHEEL
air_drf_relation-1.0.3.dist-info/licenses/LICENSE
air_drf_relation-1.0.3.dist-info/RECORD
