Metadata-Version: 2.4
Name: air-drf-relation
Version: 1.0.3
Summary: Enhanced Django REST Framework serializers with advanced relation handling, queryset optimization, and type safety
Project-URL: Documentation, https://github.com/bubaley/air-drf-relation#readme
Project-URL: Homepage, https://github.com/bubaley/air-drf-relation
Project-URL: Repository, https://github.com/bubaley/air-drf-relation.git
Author-email: bubaley <bubaley.fu@gmail.com>
Maintainer-email: bubaley <bubaley.fu@gmail.com>
License: MIT
License-File: LICENSE
Keywords: django,drf,performance,preloading,queryset-optimization,relations,rest-framework,serializer
Classifier: Development Status :: 4 - Beta
Classifier: Framework :: Django
Classifier: Framework :: Django :: 4.2
Classifier: Framework :: Django :: 5.0
Classifier: Framework :: Django :: 5.1
Classifier: Framework :: Django :: 5.2
Classifier: Intended Audience :: Developers
Classifier: License :: OSI Approved :: MIT License
Classifier: Programming Language :: Python :: 3 :: Only
Classifier: Programming Language :: Python :: 3.9
Classifier: Programming Language :: Python :: 3.10
Classifier: Programming Language :: Python :: 3.11
Classifier: Programming Language :: Python :: 3.12
Classifier: Programming Language :: Python :: 3.13
Classifier: Topic :: Internet :: WWW/HTTP
Classifier: Topic :: Software Development :: Libraries :: Python Modules
Classifier: Typing :: Typed
Requires-Python: >=3.9
Requires-Dist: dacite>=1.8.1
Requires-Dist: django-filter>=21.1
Requires-Dist: django>=4.2.2
Requires-Dist: djangorestframework-dataclasses>=1.2.0
Requires-Dist: djangorestframework>=3.14.0
